{
    "comment":
    [
        "formatcheck: https://www.bejson.com/explore/index_new/",
        "lcntype: default value is share",
            "alone: when UI switch lcn on or off, the lcn value will be changed in this dtv type",
            "share: when UI switch lcn on or off, the lcn value will be changed in all dtv type",
            "alwaysoff: no care ui setting, always off",
            "alwayson: no care ui setting, always on",
        "tidydb: bit0: 0:save data service 1:remove data service, bit1:0:save duplicate service 1:remove duplicate service",
        "sortservicepriority: sort priority sort type: servicename,InTs,frequency,serviceid,servicetype,SignalLevel,Scramble,Resolution",
        "tvfirstunallocatedlcn: TV service first unallocated lcn",
        "radiofirstunallocatedlcn: radio service first unallocated lcn",
        "otherfirstunallocatedlcn: other service first unallocated lcn",
        "radiolcnoffset:  radio lcnoff set",
        " FALSE/TRUE, default is FALSE",
        "privatedatacode: if no set, use pravitedata in country setting",
        "firstunallocatedlcn: if no be set, this value is 800",
        "lastunallocatedlcn=if no be set, this value is 9999",
        "protocoltype: EACEM, NORDIG,DBOOK,SEA, OTHER",
        "netidmax=0xffff;orignetidmax=0xffff",
        "needmatchonid: this country must match onid list,",
        "presortfilename: customer lcn file",
        "the end"
    ],

    "cfgversion": 1,
    "countrydefaultvalue":
    {
        "lcntype": "share"
    },
    "countrylist": [
        {
            "description": "ARGENTINA",
            "countrycode": "arg",
            "lcntype": "alwaysoff",
            "firstunallocatedlcn": "1000",
            "lastunallocatedlcn": "9999"
        },
        {
            "countrycode": "aus",
            "lcntype": "alwaysoff",
            "firstunallocatedlcn": "350",
            "lastunallocatedlcn": "399"
        },
        {
            "countrycode": "aut",
            "lcntype": "alwaysoff",
            "firstunallocatedlcn": "800",
            "lastunallocatedlcn": "9999"
        },
        {
            "countrycode": "bel",
            "lcntype": "alwaysoff",
            "firstunallocatedlcn": "800",
            "lastunallocatedlcn": "9999"
        },
        {
            "description": "BOLIVIA",
            "countrycode": "bol",
            "lcntype": "alwaysoff",
            "firstunallocatedlcn": "1000",
            "lastunallocatedlcn": "9999"
        },
        {
            "description": "BRAZIL",
            "countrycode": "bra",
            "lcntype": "alwaysoff",
            "firstunallocatedlcn": "1000",
            "lastunallocatedlcn": "9999"
        },
        {
            "description": "CHILE",
            "countrycode": "chl",
            "lcntype": "alwaysoff",
            "firstunallocatedlcn": "1000",
            "lastunallocatedlcn": "9999"
        },
        {
            "description": "COLOMBIA",
            "countrycode": "col",
            "lcntype": "alwaysoff",
            "firstunallocatedlcn": "1000",
            "lastunallocatedlcn": "9999"
        },
        {
            "description": "COSTARICA",
            "countrycode": "cri",
            "lcntype": "alwaysoff",
            "firstunallocatedlcn": "1000",
            "lastunallocatedlcn": "9999"
        },
        {
            "description": "CZECHREP",
            "countrycode": "cze",
            "lcntype": "alwaysoff",
            "firstunallocatedlcn": "800",
            "lastunallocatedlcn": "9999"
        },
        {
            "description": "GERMANY",
            "countrycode": "deu",
            "lcntype": "share",
            "firstunallocatedlcn": "3000",
            "lastunallocatedlcn": "3999",
            "tidydb": "0x00",
            "operatorsList": [
                {
                    "name": "Sky Deutschland",
                    "code": "0x0001",
                    "firstunallocatedlcn": "300",
                    "lastunallocatedlcn": "9999",
                    "tidydb": "0x01",
                    "frequencylist": "satellite_deu_sky.json"
                }
            ]
        },
        {
            "description": "DOMINICA",
            "countrycode": "dma",
            "lcntype": "alwaysoff",
            "firstunallocatedlcn": "1000",
            "lastunallocatedlcn": "9999"
        },
        {
            "countrycode": "dnk",
            "lcntype": "alwaysoff",
            "firstunallocatedlcn": "1000",
            "lastunallocatedlcn": "9999"
        },
        {
            "description": "ECUADOR",
            "countrycode": "ecu",
            "lcntype": "alwaysoff",
            "firstunallocatedlcn": "1000",
            "lastunallocatedlcn": "9999"
        },
        {
            "description": "ELSALVADOR",
            "countrycode": "slv",
            "lcntype": "alwaysoff",
            "firstunallocatedlcn": "1000",
            "lastunallocatedlcn": "9999"
        },
        {
            "countrycode": "est",
            "lcntype": "alwaysoff",
            "firstunallocatedlcn": "800",
            "lastunallocatedlcn": "9999"
        },
        {
            "countrycode": "fin",
            "lcntype": "alwaysoff",
            "firstunallocatedlcn": "800",
            "lastunallocatedlcn": "899"
        },
        {
            "countrycode": "fra",
            "lcntype": "alwaysoff",
            "firstunallocatedlcn": "800",
            "lastunallocatedlcn": "899"
        },
        {
            "countrycode": "gbr",
            "lcntype": "alwaysoff",
            "firstunallocatedlcn": "1000",
            "lastunallocatedlcn": "9999"
        },
        {
            "countrycode": "hrv",
            "lcntype": "alwaysoff",
            "firstunallocatedlcn": "800",
            "lastunallocatedlcn": "9999"
        },
        {
            "countrycode": "isl",
            "lcntype": "alwaysoff",
            "firstunallocatedlcn": "800",
            "lastunallocatedlcn": "9999"
        },
        {
            "countrycode": "ita",
            "lcntype": "alwaysoff",
            "firstunallocatedlcn": "850",
            "lastunallocatedlcn": "999"
        },
        {
            "countrycode": "nor",
            "lcntype": "alwaysoff",
            "firstunallocatedlcn": "0",
            "lastunallocatedlcn": "899"
        },
        {
            "countrycode": "nzl",
            "lcntype": "alwaysoff",
            "firstunallocatedlcn": "800",
            "lastunallocatedlcn": "9999"
        },
        {
            "countrycode": "rus",
            "lcntype": "alwaysoff",
            "firstunallocatedlcn": "800",
            "lastunallocatedlcn": "899"
        },
        {
            "countrycode": "srb",
            "lcntype": "alwaysoff",
            "firstunallocatedlcn": "800",
            "lastunallocatedlcn": "9999"
        },
        {
            "countrycode": "swe",
            "lcntype": "alwaysoff",
            "firstunallocatedlcn": "800",
            "lastunallocatedlcn": "9999"
        },
        {
            "countrycode": "tur",
            "lcntype": "share",
            "firstunallocatedlcn": "800",
            "lastunallocatedlcn": "899",
            "operatorsList": [
                {
                    "name": "TKGS",
                    "code": "0x0301",
                    "lcntype": "share"
                },
                {
                    "countrycode": "tur",
                    "name": "Other Operators",
                    "code": "0xffff",
                    "lcntype": "alwaysoff"
                }
            ]
        },
        {
            "countrycode": "ukr",
            "lcntype": "alwaysoff",
            "firstunallocatedlcn": "800",
            "lastunallocatedlcn": "9999"
        }
    ],
    "countrydataexample":
    {
        "countrycode": "deu",
        "lcntype": "Share",
        "firstunallocatedlcn": "3000",
        "lastunallocatedlcn": "9999",
        "tidydb": "0x00",
        "beouquetid":"0x111",
        "frequencylist": "satellite_deu_sky.json",
        "protocoltype":"EACEM",
        "netidmax":"0xffff",
        "orignetidmax":"0xffff",
        "needmatchonid":["0x2114","0x0085","0x22f1"],
        "privatedatacode": ["0x28","0x66","0x88"],
        "presortfilename":"xxxxxx.json",
        "lcnon":
        {
            "radiolcnoffset": "0",
            "otherlcnoffset":"0",
            "servicesorttype":["servicename","servicetype","serviceid","frequency"]
        },
        "lcnoff":
        {
            "tvfirstunallocatedlcn":"1",
            "radiofirstunallocatedlcn": "0",
            "otherfirstunallocatedlcn":"0",
            "servicesorttype":["servicename","servicetype","serviceid","frequency"]
        },
        "operatorsList": [
            {
                "name": "Astra HD+",
                "code": "0x0000",
                "privatedatacode": ["0x28","0x66","0x88"],
                "firstunallocatedlcn": "800",
                "lastunallocatedlcn": "9999",
                "tidydb": "0x01",
                "frequencylist": "satellite_deu_sky.json"
            },
            {
                "name": "Sky Deutschland",
                "code": "0x0001",
                "privatedatacode": ["0x28","0x66","0x88"],
                "firstunallocatedlcn": "300",
                "lastunallocatedlcn": "9999",
                "tidydb": "0x01",
                "frequencylist": "satellite_deu_sky.json"
            }
        ]
    }
}
